pyhdbcli.abi3.so
hdbcli/__init__.py
hdbcli/dbapi.py
hdbcli/resultrow.py
hdbcli-2.27.23.dist-info/licenses/LICENSE
hdbcli-2.27.23.dist-info/METADATA
hdbcli-2.27.23.dist-info/WHEEL
hdbcli-2.27.23.dist-info/top_level.txt
hdbcli-2.27.23.dist-info/RECORD
